sigmaiq/.gitignore
sigmaiq/__init__.py
sigmaiq/backends/__init__.py
sigmaiq/backends/carbonblack/__init__.py
sigmaiq/backends/carbonblack/carbonblack.py
sigmaiq/backends/cortexxdr/__init__.py
sigmaiq/backends/cortexxdr/cortexxdr.py
sigmaiq/backends/crowdstrike/__init__.py
sigmaiq/backends/crowdstrike/crowdstrike.py
sigmaiq/backends/elasticsearch/__init__.py
sigmaiq/backends/elasticsearch/elasticsearch.py
sigmaiq/backends/insightidr/__init__.py
sigmaiq/backends/insightidr/insightidr.py
sigmaiq/backends/kusto/__init__.py
sigmaiq/backends/kusto/kusto.py
sigmaiq/backends/netwitness/__init__.py
sigmaiq/backends/netwitness/netwitness.py
sigmaiq/backends/opensearch/__init__.py
sigmaiq/backends/opensearch/opensearch.py
sigmaiq/backends/qradar/__init__.py
sigmaiq/backends/qradar/qradar.py
sigmaiq/backends/secops/__init__.py
sigmaiq/backends/secops/secops.py
sigmaiq/backends/sentinelone/__init__.py
sigmaiq/backends/sentinelone/sentinelone.py
sigmaiq/backends/sigma/__init__.py
sigmaiq/backends/sigma/sigma.py
sigmaiq/backends/sigmaiq_abstract_backend.py
sigmaiq/backends/splunk/__init__.py
sigmaiq/backends/splunk/savedsearches_template.txt
sigmaiq/backends/splunk/splunk.py
sigmaiq/backends/stix/__init__.py
sigmaiq/backends/stix/stix.py
sigmaiq/exceptions.py
sigmaiq/globals.py
sigmaiq/llm/README.md
sigmaiq/llm/__init__.py
sigmaiq/llm/base.py
sigmaiq/llm/toolkits/__init__.py
sigmaiq/llm/toolkits/base.py
sigmaiq/llm/toolkits/prompts.py
sigmaiq/llm/toolkits/sigma_toolkit.py
sigmaiq/llm/tools/__init__.py
sigmaiq/llm/tools/create_sigma_rule.py
sigmaiq/llm/tools/find_sigma_rule.py
sigmaiq/llm/tools/query_to_sigma_rule.py
sigmaiq/llm/tools/translate_sigma_rule.py
sigmaiq/pipelines/__init__.py
sigmaiq/pipelines/splunk_windows_audit/__init__.py
sigmaiq/pipelines/splunk_windows_audit/splunk_wineventlog.py
sigmaiq/sigmaiq_backend_factory.py
sigmaiq/sigmaiq_pipeline_factory.py
sigmaiq/utils/sigma/__init__.py
sigmaiq/utils/sigma/rule_updater.py
sigmaiq/utils/sigmaiq/__init__.py
sigmaiq-0.5.0.dist-info/METADATA
sigmaiq-0.5.0.dist-info/WHEEL
sigmaiq-0.5.0.dist-info/licenses/LICENSE
sigmaiq-0.5.0.dist-info/RECORD
