Metadata-Version: 2.4
Name: SigmAIQ
Version: 0.5.0
Summary: Wrapper and tools for pySigma and Sigma rules
License-File: LICENSE
Author: Stephen Lincoln
Author-email: stephen.lincoln@attackiq.com
Requires-Python: >=3.9,<3.14
Classifier: Development Status :: 4 - Beta
Classifier: Intended Audience :: Developers
Classifier: License :: OSI Approved :: GNU Lesser General Public License v2 (LGPLv2)
Classifier: Programming Language :: Python :: 3
Classifier: Programming Language :: Python :: 3.9
Classifier: Programming Language :: Python :: 3.10
Classifier: Programming Language :: Python :: 3.11
Classifier: Programming Language :: Python :: 3.12
Classifier: Programming Language :: Python :: 3.13
Classifier: Programming Language :: Python :: 3.8
Classifier: Topic :: Security
Provides-Extra: llm
Requires-Dist: certifi (>=2024.8.30)
Requires-Dist: faiss-cpu ; extra == "llm"
Requires-Dist: importlib-resources (>=5.13.0,<6.0.0)
Requires-Dist: langchain (>=0.2.9,<0.3.0) ; extra == "llm"
Requires-Dist: langchain-community (>=0.2.7,<0.3.0) ; extra == "llm"
Requires-Dist: langchain-core (>=0.2.20,<0.3.0) ; extra == "llm"
Requires-Dist: langchain-openai (>=0.1.17,<0.2.0) ; extra == "llm"
Requires-Dist: openai ; extra == "llm"
Requires-Dist: pysigma (==0.11.18)
Requires-Dist: pysigma-backend-carbonblack (==0.1.8)
Requires-Dist: pysigma-backend-cortexxdr (==0.1.4)
Requires-Dist: pysigma-backend-crowdstrike (==2.0.1)
Requires-Dist: pysigma-backend-elasticsearch (==1.1.3)
Requires-Dist: pysigma-backend-insightidr (==0.2.4)
Requires-Dist: pysigma-backend-kusto (==0.4.2)
Requires-Dist: pysigma-backend-netwitness (==0.1.3)
Requires-Dist: pysigma-backend-opensearch (==1.0.3)
Requires-Dist: pysigma-backend-qradar-aql (==0.3.2)
Requires-Dist: pysigma-backend-secops (==0.1.4)
Requires-Dist: pysigma-backend-sentinelone (==0.1.3)
Requires-Dist: pysigma-backend-splunk (==1.1.0)
Requires-Dist: pysigma-backend-stix2 (==0.2.0)
Requires-Dist: pysigma-pipeline-sysmon (==1.0.4)
Requires-Dist: pysigma-pipeline-windows (==1.2.0)
Requires-Dist: tiktoken ; extra == "llm"
